README.md
setup.py
fs_django_sberbank.egg-info/PKG-INFO
fs_django_sberbank.egg-info/SOURCES.txt
fs_django_sberbank.egg-info/dependency_links.txt
fs_django_sberbank.egg-info/not-zip-safe
fs_django_sberbank.egg-info/requires.txt
fs_django_sberbank.egg-info/top_level.txt
sberbank/__init__.py
sberbank/admin.py
sberbank/apps.py
sberbank/exceptions.py
sberbank/models.py
sberbank/sberbank_settings.py
sberbank/serializers.py
sberbank/service.py
sberbank/tasks.py
sberbank/urls.py
sberbank/util.py
sberbank/views.py
sberbank/migrations/0001_initial.py
sberbank/migrations/0002_auto_20180802_1820.py
sberbank/migrations/0003_auto_20180804_1932.py
sberbank/migrations/0004_logentry_request_text.py
sberbank/migrations/0005_auto_20180831_0901.py
sberbank/migrations/0006_payment_method.py
sberbank/migrations/0007_auto_20191204_1542.py
sberbank/migrations/0008_payment_order_number.py
sberbank/migrations/__init__.py