Metadata-Version: 1.1
Name: fs-django-sberbank
Version: 0.2.35
Summary: Django app for Sberbank payments
Home-page: http://github.com/madprogrammer/django-sberbank
Author: Sergey Anufrienko
Author-email: sergey.anoufrienko@gmail.com
License: BSD
Platform: any
Classifier: Programming Language :: Python :: 3
Classifier: License :: OSI Approved :: BSD License
Classifier: Operating System :: OS Independent
